Metadata-Version: 2.4
Name: jarvis-nlp
Version: 7.2.0
Summary: Voice-Activated Natural Language UI
Author-email: Vignesh Rao <svignesh1793@gmail.com>
License: MIT License
Project-URL: API, https://jarvis.vigneshrao.com
Project-URL: Health, https://jarvis-health.vigneshrao.com
Project-URL: Homepage, https://github.com/thevickypedia/Jarvis
Project-URL: Docs, https://jarvis-docs.vigneshrao.com
Project-URL: Demo, https://vigneshrao.com/Jarvis/Jarvis_Demo.mp4
Project-URL: Source, https://github.com/thevickypedia/Jarvis
Project-URL: Bug Tracker, https://github.com/thevickypedia/Jarvis/issues
Project-URL: Release Notes, https://github.com/thevickypedia/Jarvis/blob/master/release_notes.rst
Keywords: python,home-automation,natural-language-processing,text-to-speech,speech-recognition,jarvis,hotword-detection,virtual-assistant
Classifier: Development Status :: 5 - Production/Stable
Classifier: Intended Audience :: Information Technology
Classifier: Operating System :: MacOS :: MacOS X
Classifier: Operating System :: Microsoft :: Windows :: Windows 10
Classifier: Operating System :: POSIX :: Linux
Classifier: License :: OSI Approved :: MIT License
Classifier: Programming Language :: Python :: 3.10
Classifier: Programming Language :: Python :: 3.11
Classifier: Topic :: Multimedia :: Sound/Audio :: Speech
Classifier: Topic :: Scientific/Engineering :: Human Machine Interfaces
Classifier: Topic :: Scientific/Engineering :: Artificial Intelligence
Classifier: Topic :: Home Automation
Classifier: Topic :: Scientific/Engineering :: Image Recognition
Classifier: Topic :: System :: Hardware :: Universal Serial Bus (USB) :: Wireless Controller
Classifier: Topic :: Multimedia :: Sound/Audio :: Conversion
Classifier: Topic :: Software Development :: Libraries :: Python Modules
Classifier: Topic :: System :: Hardware :: Hardware Drivers
Classifier: Topic :: System :: Hardware :: Symmetric Multi-processing
Classifier: Framework :: AnyIO
Classifier: Framework :: FastAPI
Classifier: Framework :: AsyncIO
Classifier: Framework :: Pydantic :: 2
Classifier: Framework :: Setuptools Plugin
Classifier: Framework :: aiohttp
Classifier: Natural Language :: English
Requires-Python: <3.12,>=3.10
License-File: LICENSE
Provides-Extra: dev
Requires-Dist: sphinx==5.1.1; extra == "dev"
Requires-Dist: pre-commit; extra == "dev"
Requires-Dist: recommonmark; extra == "dev"
Requires-Dist: pytest; extra == "dev"
Requires-Dist: gitverse; extra == "dev"
Dynamic: license-file
